[
    {
        "name": "BeginStep",
        "ph": "B",
        "ts": 1705358060160112,
        "pid": 154444,
        "tid": 140364301159616
    },
    {
        "name": "IncrementCurrentStep",
        "ph": "B",
        "ts": 1705358060160176,
        "pid": 154444,
        "tid": 140364301159616
    },
    {
        "name": "IncrementCurrentStep",
        "ph": "E",
        "ts": 1705358060160194,
        "pid": 154444,
        "tid": 140364301159616
    },
    {
        "name": "GetBucket",
        "ph": "B",
        "ts": 1705358060160233,
        "pid": 154444,
        "tid": 140364301159616
    },
    {
        "name": "GetBucket",
        "ph": "E",
        "ts": 1705358060160882,
        "pid": 154444,
        "tid": 140364301159616
    },
    {
        "name": "BeginStep",
        "ph": "E",
        "ts": 1705358060160924,
        "pid": 154444,
        "tid": 140364301159616
    },
    {
        "name": "DoPutSync_",
        "ph": "B",
        "ts": 1705358060160992,
        "pid": 154444,
        "tid": 140364301159616
    },
    {
        "name": "Put",
        "ph": "B",
        "ts": 1705358060161026,
        "pid": 154444,
        "tid": 140364301159616
    },
    {
        "name": "Put",
        "ph": "E",
        "ts": 1705358060161108,
        "pid": 154444,
        "tid": 140364301159616
    },
    {
        "name": "DoPutSync_",
        "ph": "E",
        "ts": 1705358060161413,
        "pid": 154444,
        "tid": 140364301159616
    },
    {
        "name": "DoPutSync_",
        "ph": "B",
        "ts": 1705358060161442,
        "pid": 154444,
        "tid": 140364301159616
    },
    {
        "name": "Put",
        "ph": "B",
        "ts": 1705358060161459,
        "pid": 154444,
        "tid": 140364301159616
    },
    {
        "name": "Put",
        "ph": "E",
        "ts": 1705358060161515,
        "pid": 154444,
        "tid": 140364301159616
    },
    {
        "name": "DoPutSync_",
        "ph": "E",
        "ts": 1705358060161621,
        "pid": 154444,
        "tid": 140364301159616
    },
    {
        "name": "DoPutSync_",
        "ph": "B",
        "ts": 1705358060161653,
        "pid": 154444,
        "tid": 140364301159616
    },
    {
        "name": "Put",
        "ph": "B",
        "ts": 1705358060161671,
        "pid": 154444,
        "tid": 140364301159616
    },
    {
        "name": "Put",
        "ph": "E",
        "ts": 1705358060161721,
        "pid": 154444,
        "tid": 140364301159616
    },
    {
        "name": "DoPutSync_",
        "ph": "E",
        "ts": 1705358060161826,
        "pid": 154444,
        "tid": 140364301159616
    },
    {
        "name": "DoPutSync_",
        "ph": "B",
        "ts": 1705358060161844,
        "pid": 154444,
        "tid": 140364301159616
    },
    {
        "name": "Put",
        "ph": "B",
        "ts": 1705358060161860,
        "pid": 154444,
        "tid": 140364301159616
    },
    {
        "name": "Put",
        "ph": "E",
        "ts": 1705358060161906,
        "pid": 154444,
        "tid": 140364301159616
    },
    {
        "name": "DoPutSync_",
        "ph": "E",
        "ts": 1705358060162007,
        "pid": 154444,
        "tid": 140364301159616
    },
    {
        "name": "DoPutSync_",
        "ph": "B",
        "ts": 1705358060162028,
        "pid": 154444,
        "tid": 140364301159616
    },
    {
        "name": "Put",
        "ph": "B",
        "ts": 1705358060162043,
        "pid": 154444,
        "tid": 140364301159616
    },
    {
        "name": "Put",
        "ph": "E",
        "ts": 1705358060162088,
        "pid": 154444,
        "tid": 140364301159616
    },
    {
        "name": "DoPutSync_",
        "ph": "E",
        "ts": 1705358060162189,
        "pid": 154444,
        "tid": 140364301159616
    },
    {
        "name": "DoPutSync_",
        "ph": "B",
        "ts": 1705358060162207,
        "pid": 154444,
        "tid": 140364301159616
    },
    {
        "name": "Put",
        "ph": "B",
        "ts": 1705358060162222,
        "pid": 154444,
        "tid": 140364301159616
    },
    {
        "name": "Put",
        "ph": "E",
        "ts": 1705358060162277,
        "pid": 154444,
        "tid": 140364301159616
    },
    {
        "name": "DoPutSync_",
        "ph": "E",
        "ts": 1705358060162377,
        "pid": 154444,
        "tid": 140364301159616
    },
    {
        "name": "DoPutSync_",
        "ph": "B",
        "ts": 1705358060162395,
        "pid": 154444,
        "tid": 140364301159616
    },
    {
        "name": "Put",
        "ph": "B",
        "ts": 1705358060162410,
        "pid": 154444,
        "tid": 140364301159616
    },
    {
        "name": "Put",
        "ph": "E",
        "ts": 1705358060162458,
        "pid": 154444,
        "tid": 140364301159616
    },
    {
        "name": "DoPutSync_",
        "ph": "E",
        "ts": 1705358060162559,
        "pid": 154444,
        "tid": 140364301159616
    },
    {
        "name": "DoPutSync_",
        "ph": "B",
        "ts": 1705358060162577,
        "pid": 154444,
        "tid": 140364301159616
    },
    {
        "name": "Put",
        "ph": "B",
        "ts": 1705358060162592,
        "pid": 154444,
        "tid": 140364301159616
    },
    {
        "name": "Put",
        "ph": "E",
        "ts": 1705358060162639,
        "pid": 154444,
        "tid": 140364301159616
    },
    {
        "name": "DoPutSync_",
        "ph": "E",
        "ts": 1705358060162743,
        "pid": 154444,
        "tid": 140364301159616
    },
    {
        "name": "DoPutSync_",
        "ph": "B",
        "ts": 1705358060162765,
        "pid": 154444,
        "tid": 140364301159616
    },
    {
        "name": "Put",
        "ph": "B",
        "ts": 1705358060162780,
        "pid": 154444,
        "tid": 140364301159616
    },
    {
        "name": "Put",
        "ph": "E",
        "ts": 1705358060162825,
        "pid": 154444,
        "tid": 140364301159616
    },
    {
        "name": "DoPutSync_",
        "ph": "E",
        "ts": 1705358060162927,
        "pid": 154444,
        "tid": 140364301159616
    },
    {
        "name": "DoPutSync_",
        "ph": "B",
        "ts": 1705358060162945,
        "pid": 154444,
        "tid": 140364301159616
    },
    {
        "name": "Put",
        "ph": "B",
        "ts": 1705358060162966,
        "pid": 154444,
        "tid": 140364301159616
    },
    {
        "name": "Put",
        "ph": "E",
        "ts": 1705358060163017,
        "pid": 154444,
        "tid": 140364301159616
    },
    {
        "name": "DoPutSync_",
        "ph": "E",
        "ts": 1705358060163120,
        "pid": 154444,
        "tid": 140364301159616
    },
    {
        "name": "DoPutSync_",
        "ph": "B",
        "ts": 1705358060163138,
        "pid": 154444,
        "tid": 140364301159616
    },
    {
        "name": "Put",
        "ph": "B",
        "ts": 1705358060163155,
        "pid": 154444,
        "tid": 140364301159616
    },
    {
        "name": "Put",
        "ph": "E",
        "ts": 1705358060163218,
        "pid": 154444,
        "tid": 140364301159616
    },
    {
        "name": "DoPutSync_",
        "ph": "E",
        "ts": 1705358060163344,
        "pid": 154444,
        "tid": 140364301159616
    },
    {
        "name": "DoPutSync_",
        "ph": "B",
        "ts": 1705358060163363,
        "pid": 154444,
        "tid": 140364301159616
    },
    {
        "name": "Put",
        "ph": "B",
        "ts": 1705358060163379,
        "pid": 154444,
        "tid": 140364301159616
    },
    {
        "name": "Put",
        "ph": "E",
        "ts": 1705358060163427,
        "pid": 154444,
        "tid": 140364301159616
    },
    {
        "name": "DoPutSync_",
        "ph": "E",
        "ts": 1705358060163534,
        "pid": 154444,
        "tid": 140364301159616
    },
    {
        "name": "DoPutDeferred_",
        "ph": "B",
        "ts": 1705358060163560,
        "pid": 154444,
        "tid": 140364301159616
    },
    {
        "name": "Put",
        "ph": "B",
        "ts": 1705358060163576,
        "pid": 154444,
        "tid": 140364301159616
    },
    {
        "name": "Put",
        "ph": "E",
        "ts": 1705358060163812,
        "pid": 154444,
        "tid": 140364301159616
    },
    {
        "name": "DoPutDeferred_",
        "ph": "E",
        "ts": 1705358060163924,
        "pid": 154444,
        "tid": 140364301159616
    },
    {
        "name": "EndStep",
        "ph": "B",
        "ts": 1705358060163942,
        "pid": 154444,
        "tid": 140364301159616
    },
    {
        "name": "EndStep",
        "ph": "E",
        "ts": 1705358060164041,
        "pid": 154444,
        "tid": 140364301159616
    },
    {
        "name": "BeginStep",
        "ph": "B",
        "ts": 1705358060526656,
        "pid": 154444,
        "tid": 140364301159616
    },
    {
        "name": "IncrementCurrentStep",
        "ph": "B",
        "ts": 1705358060526686,
        "pid": 154444,
        "tid": 140364301159616
    },
    {
        "name": "IncrementCurrentStep",
        "ph": "E",
        "ts": 1705358060526701,
        "pid": 154444,
        "tid": 140364301159616
    },
    {
        "name": "GetBucket",
        "ph": "B",
        "ts": 1705358060526744,
        "pid": 154444,
        "tid": 140364301159616
    },
    {
        "name": "BeginStep",
        "ph": "B",
        "ts": 1705358060159980,
        "pid": 154445,
        "tid": 139843281267904
    },
    {
        "name": "IncrementCurrentStep",
        "ph": "B",
        "ts": 1705358060160045,
        "pid": 154445,
        "tid": 139843281267904
    },
    {
        "name": "IncrementCurrentStep",
        "ph": "E",
        "ts": 1705358060160063,
        "pid": 154445,
        "tid": 139843281267904
    },
    {
        "name": "GetBucket",
        "ph": "B",
        "ts": 1705358060160102,
        "pid": 154445,
        "tid": 139843281267904
    },
    {
        "name": "GetBucket",
        "ph": "E",
        "ts": 1705358060160221,
        "pid": 154445,
        "tid": 139843281267904
    },
    {
        "name": "BeginStep",
        "ph": "E",
        "ts": 1705358060160263,
        "pid": 154445,
        "tid": 139843281267904
    },
    {
        "name": "DoPutSync_",
        "ph": "B",
        "ts": 1705358060160392,
        "pid": 154445,
        "tid": 139843281267904
    },
    {
        "name": "Put",
        "ph": "B",
        "ts": 1705358060160964,
        "pid": 154445,
        "tid": 139843281267904
    },
    {
        "name": "Put",
        "ph": "E",
        "ts": 1705358060161058,
        "pid": 154445,
        "tid": 139843281267904
    },
    {
        "name": "DoPutSync_",
        "ph": "E",
        "ts": 1705358060161383,
        "pid": 154445,
        "tid": 139843281267904
    },
    {
        "name": "DoPutSync_",
        "ph": "B",
        "ts": 1705358060161415,
        "pid": 154445,
        "tid": 139843281267904
    },
    {
        "name": "Put",
        "ph": "B",
        "ts": 1705358060161433,
        "pid": 154445,
        "tid": 139843281267904
    },
    {
        "name": "Put",
        "ph": "E",
        "ts": 1705358060161482,
        "pid": 154445,
        "tid": 139843281267904
    },
    {
        "name": "DoPutSync_",
        "ph": "E",
        "ts": 1705358060161590,
        "pid": 154445,
        "tid": 139843281267904
    },
    {
        "name": "DoPutSync_",
        "ph": "B",
        "ts": 1705358060161623,
        "pid": 154445,
        "tid": 139843281267904
    },
    {
        "name": "Put",
        "ph": "B",
        "ts": 1705358060161641,
        "pid": 154445,
        "tid": 139843281267904
    },
    {
        "name": "Put",
        "ph": "E",
        "ts": 1705358060161687,
        "pid": 154445,
        "tid": 139843281267904
    },
    {
        "name": "DoPutSync_",
        "ph": "E",
        "ts": 1705358060161796,
        "pid": 154445,
        "tid": 139843281267904
    },
    {
        "name": "DoPutSync_",
        "ph": "B",
        "ts": 1705358060161815,
        "pid": 154445,
        "tid": 139843281267904
    },
    {
        "name": "Put",
        "ph": "B",
        "ts": 1705358060161831,
        "pid": 154445,
        "tid": 139843281267904
    },
    {
        "name": "Put",
        "ph": "E",
        "ts": 1705358060161877,
        "pid": 154445,
        "tid": 139843281267904
    },
    {
        "name": "DoPutSync_",
        "ph": "E",
        "ts": 1705358060161987,
        "pid": 154445,
        "tid": 139843281267904
    },
    {
        "name": "DoPutSync_",
        "ph": "B",
        "ts": 1705358060162006,
        "pid": 154445,
        "tid": 139843281267904
    },
    {
        "name": "Put",
        "ph": "B",
        "ts": 1705358060162021,
        "pid": 154445,
        "tid": 139843281267904
    },
    {
        "name": "Put",
        "ph": "E",
        "ts": 1705358060162067,
        "pid": 154445,
        "tid": 139843281267904
    },
    {
        "name": "DoPutSync_",
        "ph": "E",
        "ts": 1705358060162170,
        "pid": 154445,
        "tid": 139843281267904
    },
    {
        "name": "DoPutSync_",
        "ph": "B",
        "ts": 1705358060162188,
        "pid": 154445,
        "tid": 139843281267904
    },
    {
        "name": "Put",
        "ph": "B",
        "ts": 1705358060162204,
        "pid": 154445,
        "tid": 139843281267904
    },
    {
        "name": "Put",
        "ph": "E",
        "ts": 1705358060162249,
        "pid": 154445,
        "tid": 139843281267904
    },
    {
        "name": "DoPutSync_",
        "ph": "E",
        "ts": 1705358060162351,
        "pid": 154445,
        "tid": 139843281267904
    },
    {
        "name": "DoPutSync_",
        "ph": "B",
        "ts": 1705358060162369,
        "pid": 154445,
        "tid": 139843281267904
    },
    {
        "name": "Put",
        "ph": "B",
        "ts": 1705358060162385,
        "pid": 154445,
        "tid": 139843281267904
    },
    {
        "name": "Put",
        "ph": "E",
        "ts": 1705358060162433,
        "pid": 154445,
        "tid": 139843281267904
    },
    {
        "name": "DoPutSync_",
        "ph": "E",
        "ts": 1705358060162531,
        "pid": 154445,
        "tid": 139843281267904
    },
    {
        "name": "DoPutSync_",
        "ph": "B",
        "ts": 1705358060162549,
        "pid": 154445,
        "tid": 139843281267904
    },
    {
        "name": "Put",
        "ph": "B",
        "ts": 1705358060162565,
        "pid": 154445,
        "tid": 139843281267904
    },
    {
        "name": "Put",
        "ph": "E",
        "ts": 1705358060162613,
        "pid": 154445,
        "tid": 139843281267904
    },
    {
        "name": "DoPutSync_",
        "ph": "E",
        "ts": 1705358060162715,
        "pid": 154445,
        "tid": 139843281267904
    },
    {
        "name": "DoPutSync_",
        "ph": "B",
        "ts": 1705358060162736,
        "pid": 154445,
        "tid": 139843281267904
    },
    {
        "name": "Put",
        "ph": "B",
        "ts": 1705358060162752,
        "pid": 154445,
        "tid": 139843281267904
    },
    {
        "name": "Put",
        "ph": "E",
        "ts": 1705358060162801,
        "pid": 154445,
        "tid": 139843281267904
    },
    {
        "name": "DoPutSync_",
        "ph": "E",
        "ts": 1705358060162906,
        "pid": 154445,
        "tid": 139843281267904
    },
    {
        "name": "DoPutSync_",
        "ph": "B",
        "ts": 1705358060162925,
        "pid": 154445,
        "tid": 139843281267904
    },
    {
        "name": "Put",
        "ph": "B",
        "ts": 1705358060162945,
        "pid": 154445,
        "tid": 139843281267904
    },
    {
        "name": "Put",
        "ph": "E",
        "ts": 1705358060163000,
        "pid": 154445,
        "tid": 139843281267904
    },
    {
        "name": "DoPutSync_",
        "ph": "E",
        "ts": 1705358060163101,
        "pid": 154445,
        "tid": 139843281267904
    },
    {
        "name": "DoPutSync_",
        "ph": "B",
        "ts": 1705358060163121,
        "pid": 154445,
        "tid": 139843281267904
    },
    {
        "name": "Put",
        "ph": "B",
        "ts": 1705358060163139,
        "pid": 154445,
        "tid": 139843281267904
    },
    {
        "name": "Put",
        "ph": "E",
        "ts": 1705358060163186,
        "pid": 154445,
        "tid": 139843281267904
    },
    {
        "name": "DoPutSync_",
        "ph": "E",
        "ts": 1705358060163308,
        "pid": 154445,
        "tid": 139843281267904
    },
    {
        "name": "DoPutSync_",
        "ph": "B",
        "ts": 1705358060163327,
        "pid": 154445,
        "tid": 139843281267904
    },
    {
        "name": "Put",
        "ph": "B",
        "ts": 1705358060163342,
        "pid": 154445,
        "tid": 139843281267904
    },
    {
        "name": "Put",
        "ph": "E",
        "ts": 1705358060163391,
        "pid": 154445,
        "tid": 139843281267904
    },
    {
        "name": "DoPutSync_",
        "ph": "E",
        "ts": 1705358060163501,
        "pid": 154445,
        "tid": 139843281267904
    },
    {
        "name": "DoPutDeferred_",
        "ph": "B",
        "ts": 1705358060163525,
        "pid": 154445,
        "tid": 139843281267904
    },
    {
        "name": "Put",
        "ph": "B",
        "ts": 1705358060163542,
        "pid": 154445,
        "tid": 139843281267904
    },
    {
        "name": "Put",
        "ph": "E",
        "ts": 1705358060163780,
        "pid": 154445,
        "tid": 139843281267904
    },
    {
        "name": "DoPutDeferred_",
        "ph": "E",
        "ts": 1705358060163898,
        "pid": 154445,
        "tid": 139843281267904
    },
    {
        "name": "EndStep",
        "ph": "B",
        "ts": 1705358060163916,
        "pid": 154445,
        "tid": 139843281267904
    },
    {
        "name": "EndStep",
        "ph": "E",
        "ts": 1705358060163981,
        "pid": 154445,
        "tid": 139843281267904
    },
    {
        "name": "BeginStep",
        "ph": "B",
        "ts": 1705358060527902,
        "pid": 154445,
        "tid": 139843281267904
    },
    {
        "name": "IncrementCurrentStep",
        "ph": "B",
        "ts": 1705358060527934,
        "pid": 154445,
        "tid": 139843281267904
    },
    {
        "name": "IncrementCurrentStep",
        "ph": "E",
        "ts": 1705358060527950,
        "pid": 154445,
        "tid": 139843281267904
    },
    {
        "name": "GetBucket",
        "ph": "B",
        "ts": 1705358060527994,
        "pid": 154445,
        "tid": 139843281267904
    },
    {
        "name": "BeginStep",
        "ph": "B",
        "ts": 1705358060159859,
        "pid": 154446,
        "tid": 139818111577280
    },
    {
        "name": "IncrementCurrentStep",
        "ph": "B",
        "ts": 1705358060159924,
        "pid": 154446,
        "tid": 139818111577280
    },
    {
        "name": "IncrementCurrentStep",
        "ph": "E",
        "ts": 1705358060159941,
        "pid": 154446,
        "tid": 139818111577280
    },
    {
        "name": "GetBucket",
        "ph": "B",
        "ts": 1705358060159980,
        "pid": 154446,
        "tid": 139818111577280
    },
    {
        "name": "GetBucket",
        "ph": "E",
        "ts": 1705358060160656,
        "pid": 154446,
        "tid": 139818111577280
    },
    {
        "name": "BeginStep",
        "ph": "E",
        "ts": 1705358060160702,
        "pid": 154446,
        "tid": 139818111577280
    },
    {
        "name": "DoPutSync_",
        "ph": "B",
        "ts": 1705358060160759,
        "pid": 154446,
        "tid": 139818111577280
    },
    {
        "name": "Put",
        "ph": "B",
        "ts": 1705358060160970,
        "pid": 154446,
        "tid": 139818111577280
    },
    {
        "name": "Put",
        "ph": "E",
        "ts": 1705358060161058,
        "pid": 154446,
        "tid": 139818111577280
    },
    {
        "name": "DoPutSync_",
        "ph": "E",
        "ts": 1705358060161380,
        "pid": 154446,
        "tid": 139818111577280
    },
    {
        "name": "DoPutSync_",
        "ph": "B",
        "ts": 1705358060161409,
        "pid": 154446,
        "tid": 139818111577280
    },
    {
        "name": "Put",
        "ph": "B",
        "ts": 1705358060161428,
        "pid": 154446,
        "tid": 139818111577280
    },
    {
        "name": "Put",
        "ph": "E",
        "ts": 1705358060161476,
        "pid": 154446,
        "tid": 139818111577280
    },
    {
        "name": "DoPutSync_",
        "ph": "E",
        "ts": 1705358060161591,
        "pid": 154446,
        "tid": 139818111577280
    },
    {
        "name": "DoPutSync_",
        "ph": "B",
        "ts": 1705358060161623,
        "pid": 154446,
        "tid": 139818111577280
    },
    {
        "name": "Put",
        "ph": "B",
        "ts": 1705358060161641,
        "pid": 154446,
        "tid": 139818111577280
    },
    {
        "name": "Put",
        "ph": "E",
        "ts": 1705358060161699,
        "pid": 154446,
        "tid": 139818111577280
    },
    {
        "name": "DoPutSync_",
        "ph": "E",
        "ts": 1705358060161815,
        "pid": 154446,
        "tid": 139818111577280
    },
    {
        "name": "DoPutSync_",
        "ph": "B",
        "ts": 1705358060161836,
        "pid": 154446,
        "tid": 139818111577280
    },
    {
        "name": "Put",
        "ph": "B",
        "ts": 1705358060161855,
        "pid": 154446,
        "tid": 139818111577280
    },
    {
        "name": "Put",
        "ph": "E",
        "ts": 1705358060161903,
        "pid": 154446,
        "tid": 139818111577280
    },
    {
        "name": "DoPutSync_",
        "ph": "E",
        "ts": 1705358060162018,
        "pid": 154446,
        "tid": 139818111577280
    },
    {
        "name": "DoPutSync_",
        "ph": "B",
        "ts": 1705358060162040,
        "pid": 154446,
        "tid": 139818111577280
    },
    {
        "name": "Put",
        "ph": "B",
        "ts": 1705358060162058,
        "pid": 154446,
        "tid": 139818111577280
    },
    {
        "name": "Put",
        "ph": "E",
        "ts": 1705358060162103,
        "pid": 154446,
        "tid": 139818111577280
    },
    {
        "name": "DoPutSync_",
        "ph": "E",
        "ts": 1705358060162218,
        "pid": 154446,
        "tid": 139818111577280
    },
    {
        "name": "DoPutSync_",
        "ph": "B",
        "ts": 1705358060162237,
        "pid": 154446,
        "tid": 139818111577280
    },
    {
        "name": "Put",
        "ph": "B",
        "ts": 1705358060162255,
        "pid": 154446,
        "tid": 139818111577280
    },
    {
        "name": "Put",
        "ph": "E",
        "ts": 1705358060162308,
        "pid": 154446,
        "tid": 139818111577280
    },
    {
        "name": "DoPutSync_",
        "ph": "E",
        "ts": 1705358060162423,
        "pid": 154446,
        "tid": 139818111577280
    },
    {
        "name": "DoPutSync_",
        "ph": "B",
        "ts": 1705358060162443,
        "pid": 154446,
        "tid": 139818111577280
    },
    {
        "name": "Put",
        "ph": "B",
        "ts": 1705358060162461,
        "pid": 154446,
        "tid": 139818111577280
    },
    {
        "name": "Put",
        "ph": "E",
        "ts": 1705358060162515,
        "pid": 154446,
        "tid": 139818111577280
    },
    {
        "name": "DoPutSync_",
        "ph": "E",
        "ts": 1705358060162624,
        "pid": 154446,
        "tid": 139818111577280
    },
    {
        "name": "DoPutSync_",
        "ph": "B",
        "ts": 1705358060162645,
        "pid": 154446,
        "tid": 139818111577280
    },
    {
        "name": "Put",
        "ph": "B",
        "ts": 1705358060162662,
        "pid": 154446,
        "tid": 139818111577280
    },
    {
        "name": "Put",
        "ph": "E",
        "ts": 1705358060162715,
        "pid": 154446,
        "tid": 139818111577280
    },
    {
        "name": "DoPutSync_",
        "ph": "E",
        "ts": 1705358060162830,
        "pid": 154446,
        "tid": 139818111577280
    },
    {
        "name": "DoPutSync_",
        "ph": "B",
        "ts": 1705358060162854,
        "pid": 154446,
        "tid": 139818111577280
    },
    {
        "name": "Put",
        "ph": "B",
        "ts": 1705358060162872,
        "pid": 154446,
        "tid": 139818111577280
    },
    {
        "name": "Put",
        "ph": "E",
        "ts": 1705358060162924,
        "pid": 154446,
        "tid": 139818111577280
    },
    {
        "name": "DoPutSync_",
        "ph": "E",
        "ts": 1705358060163038,
        "pid": 154446,
        "tid": 139818111577280
    },
    {
        "name": "DoPutSync_",
        "ph": "B",
        "ts": 1705358060163059,
        "pid": 154446,
        "tid": 139818111577280
    },
    {
        "name": "Put",
        "ph": "B",
        "ts": 1705358060163083,
        "pid": 154446,
        "tid": 139818111577280
    },
    {
        "name": "Put",
        "ph": "E",
        "ts": 1705358060163139,
        "pid": 154446,
        "tid": 139818111577280
    },
    {
        "name": "DoPutSync_",
        "ph": "E",
        "ts": 1705358060163256,
        "pid": 154446,
        "tid": 139818111577280
    },
    {
        "name": "DoPutSync_",
        "ph": "B",
        "ts": 1705358060163287,
        "pid": 154446,
        "tid": 139818111577280
    },
    {
        "name": "Put",
        "ph": "B",
        "ts": 1705358060163308,
        "pid": 154446,
        "tid": 139818111577280
    },
    {
        "name": "Put",
        "ph": "E",
        "ts": 1705358060163362,
        "pid": 154446,
        "tid": 139818111577280
    },
    {
        "name": "DoPutSync_",
        "ph": "E",
        "ts": 1705358060163475,
        "pid": 154446,
        "tid": 139818111577280
    },
    {
        "name": "DoPutSync_",
        "ph": "B",
        "ts": 1705358060163493,
        "pid": 154446,
        "tid": 139818111577280
    },
    {
        "name": "Put",
        "ph": "B",
        "ts": 1705358060163509,
        "pid": 154446,
        "tid": 139818111577280
    },
    {
        "name": "Put",
        "ph": "E",
        "ts": 1705358060163556,
        "pid": 154446,
        "tid": 139818111577280
    },
    {
        "name": "DoPutSync_",
        "ph": "E",
        "ts": 1705358060163666,
        "pid": 154446,
        "tid": 139818111577280
    },
    {
        "name": "DoPutDeferred_",
        "ph": "B",
        "ts": 1705358060163688,
        "pid": 154446,
        "tid": 139818111577280
    },
    {
        "name": "Put",
        "ph": "B",
        "ts": 1705358060163704,
        "pid": 154446,
        "tid": 139818111577280
    },
    {
        "name": "Put",
        "ph": "E",
        "ts": 1705358060163932,
        "pid": 154446,
        "tid": 139818111577280
    },
    {
        "name": "DoPutDeferred_",
        "ph": "E",
        "ts": 1705358060164041,
        "pid": 154446,
        "tid": 139818111577280
    },
    {
        "name": "EndStep",
        "ph": "B",
        "ts": 1705358060164058,
        "pid": 154446,
        "tid": 139818111577280
    },
    {
        "name": "EndStep",
        "ph": "E",
        "ts": 1705358060164122,
        "pid": 154446,
        "tid": 139818111577280
    },
    {
        "name": "BeginStep",
        "ph": "B",
        "ts": 1705358060528169,
        "pid": 154446,
        "tid": 139818111577280
    },
    {
        "name": "IncrementCurrentStep",
        "ph": "B",
        "ts": 1705358060528202,
        "pid": 154446,
        "tid": 139818111577280
    },
    {
        "name": "IncrementCurrentStep",
        "ph": "E",
        "ts": 1705358060528216,
        "pid": 154446,
        "tid": 139818111577280
    },
    {
        "name": "GetBucket",
        "ph": "B",
        "ts": 1705358060528259,
        "pid": 154446,
        "tid": 139818111577280
    },
    {
        "name": "BeginStep",
        "ph": "B",
        "ts": 1705358060159765,
        "pid": 154447,
        "tid": 139981366099136
    },
    {
        "name": "IncrementCurrentStep",
        "ph": "B",
        "ts": 1705358060159829,
        "pid": 154447,
        "tid": 139981366099136
    },
    {
        "name": "IncrementCurrentStep",
        "ph": "E",
        "ts": 1705358060159846,
        "pid": 154447,
        "tid": 139981366099136
    },
    {
        "name": "GetBucket",
        "ph": "B",
        "ts": 1705358060159886,
        "pid": 154447,
        "tid": 139981366099136
    },
    {
        "name": "GetBucket",
        "ph": "E",
        "ts": 1705358060160015,
        "pid": 154447,
        "tid": 139981366099136
    },
    {
        "name": "BeginStep",
        "ph": "E",
        "ts": 1705358060160058,
        "pid": 154447,
        "tid": 139981366099136
    },
    {
        "name": "DoPutSync_",
        "ph": "B",
        "ts": 1705358060160392,
        "pid": 154447,
        "tid": 139981366099136
    },
    {
        "name": "Put",
        "ph": "B",
        "ts": 1705358060160964,
        "pid": 154447,
        "tid": 139981366099136
    },
    {
        "name": "Put",
        "ph": "E",
        "ts": 1705358060161059,
        "pid": 154447,
        "tid": 139981366099136
    },
    {
        "name": "DoPutSync_",
        "ph": "E",
        "ts": 1705358060161381,
        "pid": 154447,
        "tid": 139981366099136
    },
    {
        "name": "DoPutSync_",
        "ph": "B",
        "ts": 1705358060161417,
        "pid": 154447,
        "tid": 139981366099136
    },
    {
        "name": "Put",
        "ph": "B",
        "ts": 1705358060161435,
        "pid": 154447,
        "tid": 139981366099136
    },
    {
        "name": "Put",
        "ph": "E",
        "ts": 1705358060161483,
        "pid": 154447,
        "tid": 139981366099136
    },
    {
        "name": "DoPutSync_",
        "ph": "E",
        "ts": 1705358060161592,
        "pid": 154447,
        "tid": 139981366099136
    },
    {
        "name": "DoPutSync_",
        "ph": "B",
        "ts": 1705358060161623,
        "pid": 154447,
        "tid": 139981366099136
    },
    {
        "name": "Put",
        "ph": "B",
        "ts": 1705358060161641,
        "pid": 154447,
        "tid": 139981366099136
    },
    {
        "name": "Put",
        "ph": "E",
        "ts": 1705358060161687,
        "pid": 154447,
        "tid": 139981366099136
    },
    {
        "name": "DoPutSync_",
        "ph": "E",
        "ts": 1705358060161800,
        "pid": 154447,
        "tid": 139981366099136
    },
    {
        "name": "DoPutSync_",
        "ph": "B",
        "ts": 1705358060161819,
        "pid": 154447,
        "tid": 139981366099136
    },
    {
        "name": "Put",
        "ph": "B",
        "ts": 1705358060161834,
        "pid": 154447,
        "tid": 139981366099136
    },
    {
        "name": "Put",
        "ph": "E",
        "ts": 1705358060161880,
        "pid": 154447,
        "tid": 139981366099136
    },
    {
        "name": "DoPutSync_",
        "ph": "E",
        "ts": 1705358060161992,
        "pid": 154447,
        "tid": 139981366099136
    },
    {
        "name": "DoPutSync_",
        "ph": "B",
        "ts": 1705358060162011,
        "pid": 154447,
        "tid": 139981366099136
    },
    {
        "name": "Put",
        "ph": "B",
        "ts": 1705358060162026,
        "pid": 154447,
        "tid": 139981366099136
    },
    {
        "name": "Put",
        "ph": "E",
        "ts": 1705358060162072,
        "pid": 154447,
        "tid": 139981366099136
    },
    {
        "name": "DoPutSync_",
        "ph": "E",
        "ts": 1705358060162178,
        "pid": 154447,
        "tid": 139981366099136
    },
    {
        "name": "DoPutSync_",
        "ph": "B",
        "ts": 1705358060162196,
        "pid": 154447,
        "tid": 139981366099136
    },
    {
        "name": "Put",
        "ph": "B",
        "ts": 1705358060162212,
        "pid": 154447,
        "tid": 139981366099136
    },
    {
        "name": "Put",
        "ph": "E",
        "ts": 1705358060162258,
        "pid": 154447,
        "tid": 139981366099136
    },
    {
        "name": "DoPutSync_",
        "ph": "E",
        "ts": 1705358060162360,
        "pid": 154447,
        "tid": 139981366099136
    },
    {
        "name": "DoPutSync_",
        "ph": "B",
        "ts": 1705358060162378,
        "pid": 154447,
        "tid": 139981366099136
    },
    {
        "name": "Put",
        "ph": "B",
        "ts": 1705358060162393,
        "pid": 154447,
        "tid": 139981366099136
    },
    {
        "name": "Put",
        "ph": "E",
        "ts": 1705358060162441,
        "pid": 154447,
        "tid": 139981366099136
    },
    {
        "name": "DoPutSync_",
        "ph": "E",
        "ts": 1705358060162546,
        "pid": 154447,
        "tid": 139981366099136
    },
    {
        "name": "DoPutSync_",
        "ph": "B",
        "ts": 1705358060162564,
        "pid": 154447,
        "tid": 139981366099136
    },
    {
        "name": "Put",
        "ph": "B",
        "ts": 1705358060162580,
        "pid": 154447,
        "tid": 139981366099136
    },
    {
        "name": "Put",
        "ph": "E",
        "ts": 1705358060162630,
        "pid": 154447,
        "tid": 139981366099136
    },
    {
        "name": "DoPutSync_",
        "ph": "E",
        "ts": 1705358060162730,
        "pid": 154447,
        "tid": 139981366099136
    },
    {
        "name": "DoPutSync_",
        "ph": "B",
        "ts": 1705358060162754,
        "pid": 154447,
        "tid": 139981366099136
    },
    {
        "name": "Put",
        "ph": "B",
        "ts": 1705358060162769,
        "pid": 154447,
        "tid": 139981366099136
    },
    {
        "name": "Put",
        "ph": "E",
        "ts": 1705358060162817,
        "pid": 154447,
        "tid": 139981366099136
    },
    {
        "name": "DoPutSync_",
        "ph": "E",
        "ts": 1705358060162920,
        "pid": 154447,
        "tid": 139981366099136
    },
    {
        "name": "DoPutSync_",
        "ph": "B",
        "ts": 1705358060162939,
        "pid": 154447,
        "tid": 139981366099136
    },
    {
        "name": "Put",
        "ph": "B",
        "ts": 1705358060162959,
        "pid": 154447,
        "tid": 139981366099136
    },
    {
        "name": "Put",
        "ph": "E",
        "ts": 1705358060163010,
        "pid": 154447,
        "tid": 139981366099136
    },
    {
        "name": "DoPutSync_",
        "ph": "E",
        "ts": 1705358060163115,
        "pid": 154447,
        "tid": 139981366099136
    },
    {
        "name": "DoPutSync_",
        "ph": "B",
        "ts": 1705358060163136,
        "pid": 154447,
        "tid": 139981366099136
    },
    {
        "name": "Put",
        "ph": "B",
        "ts": 1705358060163153,
        "pid": 154447,
        "tid": 139981366099136
    },
    {
        "name": "Put",
        "ph": "E",
        "ts": 1705358060163205,
        "pid": 154447,
        "tid": 139981366099136
    },
    {
        "name": "DoPutSync_",
        "ph": "E",
        "ts": 1705358060163333,
        "pid": 154447,
        "tid": 139981366099136
    },
    {
        "name": "DoPutSync_",
        "ph": "B",
        "ts": 1705358060163352,
        "pid": 154447,
        "tid": 139981366099136
    },
    {
        "name": "Put",
        "ph": "B",
        "ts": 1705358060163368,
        "pid": 154447,
        "tid": 139981366099136
    },
    {
        "name": "Put",
        "ph": "E",
        "ts": 1705358060163416,
        "pid": 154447,
        "tid": 139981366099136
    },
    {
        "name": "DoPutSync_",
        "ph": "E",
        "ts": 1705358060163524,
        "pid": 154447,
        "tid": 139981366099136
    },
    {
        "name": "DoPutDeferred_",
        "ph": "B",
        "ts": 1705358060163548,
        "pid": 154447,
        "tid": 139981366099136
    },
    {
        "name": "Put",
        "ph": "B",
        "ts": 1705358060163564,
        "pid": 154447,
        "tid": 139981366099136
    },
    {
        "name": "Put",
        "ph": "E",
        "ts": 1705358060163804,
        "pid": 154447,
        "tid": 139981366099136
    },
    {
        "name": "DoPutDeferred_",
        "ph": "E",
        "ts": 1705358060163918,
        "pid": 154447,
        "tid": 139981366099136
    },
    {
        "name": "EndStep",
        "ph": "B",
        "ts": 1705358060163937,
        "pid": 154447,
        "tid": 139981366099136
    },
    {
        "name": "EndStep",
        "ph": "E",
        "ts": 1705358060164001,
        "pid": 154447,
        "tid": 139981366099136
    },
    {
        "name": "BeginStep",
        "ph": "B",
        "ts": 1705358060528025,
        "pid": 154447,
        "tid": 139981366099136
    },
    {
        "name": "IncrementCurrentStep",
        "ph": "B",
        "ts": 1705358060528058,
        "pid": 154447,
        "tid": 139981366099136
    },
    {
        "name": "IncrementCurrentStep",
        "ph": "E",
        "ts": 1705358060528073,
        "pid": 154447,
        "tid": 139981366099136
    },
    {
        "name": "GetBucket",
        "ph": "B",
        "ts": 1705358060528117,
        "pid": 154447,
        "tid": 139981366099136
    },
    {
        "name": "BeginStep",
        "ph": "B",
        "ts": 1705358086835047,
        "pid": 165488,
        "tid": 139703678176448
    },
    {
        "name": "IncrementCurrentStep",
        "ph": "B",
        "ts": 1705358086835106,
        "pid": 165488,
        "tid": 139703678176448
    },
    {
        "name": "IncrementCurrentStep",
        "ph": "E",
        "ts": 1705358086835123,
        "pid": 165488,
        "tid": 139703678176448
    },
    {
        "name": "GetBucket",
        "ph": "B",
        "ts": 1705358086835161,
        "pid": 165488,
        "tid": 139703678176448
    },
    {
        "name": "GetBucket",
        "ph": "E",
        "ts": 1705358086835280,
        "pid": 165488,
        "tid": 139703678176448
    },
    {
        "name": "BeginStep",
        "ph": "E",
        "ts": 1705358086835322,
        "pid": 165488,
        "tid": 139703678176448
    },
    {
        "name": "DoPutSync_",
        "ph": "B",
        "ts": 1705358086835362,
        "pid": 165488,
        "tid": 139703678176448
    },
    {
        "name": "Put",
        "ph": "B",
        "ts": 1705358086835596,
        "pid": 165488,
        "tid": 139703678176448
    },
    {
        "name": "Put",
        "ph": "E",
        "ts": 1705358086835680,
        "pid": 165488,
        "tid": 139703678176448
    },
    {
        "name": "DoPutSync_",
        "ph": "E",
        "ts": 1705358086836013,
        "pid": 165488,
        "tid": 139703678176448
    },
    {
        "name": "DoPutSync_",
        "ph": "B",
        "ts": 1705358086836042,
        "pid": 165488,
        "tid": 139703678176448
    },
    {
        "name": "Put",
        "ph": "B",
        "ts": 1705358086836065,
        "pid": 165488,
        "tid": 139703678176448
    },
    {
        "name": "Put",
        "ph": "E",
        "ts": 1705358086836116,
        "pid": 165488,
        "tid": 139703678176448
    },
    {
        "name": "DoPutSync_",
        "ph": "E",
        "ts": 1705358086836223,
        "pid": 165488,
        "tid": 139703678176448
    },
    {
        "name": "DoPutSync_",
        "ph": "B",
        "ts": 1705358086836250,
        "pid": 165488,
        "tid": 139703678176448
    },
    {
        "name": "Put",
        "ph": "B",
        "ts": 1705358086836268,
        "pid": 165488,
        "tid": 139703678176448
    },
    {
        "name": "Put",
        "ph": "E",
        "ts": 1705358086836313,
        "pid": 165488,
        "tid": 139703678176448
    },
    {
        "name": "DoPutSync_",
        "ph": "E",
        "ts": 1705358086836434,
        "pid": 165488,
        "tid": 139703678176448
    },
    {
        "name": "DoPutSync_",
        "ph": "B",
        "ts": 1705358086836453,
        "pid": 165488,
        "tid": 139703678176448
    },
    {
        "name": "Put",
        "ph": "B",
        "ts": 1705358086836468,
        "pid": 165488,
        "tid": 139703678176448
    },
    {
        "name": "Put",
        "ph": "E",
        "ts": 1705358086836513,
        "pid": 165488,
        "tid": 139703678176448
    },
    {
        "name": "DoPutSync_",
        "ph": "E",
        "ts": 1705358086836613,
        "pid": 165488,
        "tid": 139703678176448
    },
    {
        "name": "DoPutSync_",
        "ph": "B",
        "ts": 1705358086836631,
        "pid": 165488,
        "tid": 139703678176448
    },
    {
        "name": "Put",
        "ph": "B",
        "ts": 1705358086836646,
        "pid": 165488,
        "tid": 139703678176448
    },
    {
        "name": "Put",
        "ph": "E",
        "ts": 1705358086836694,
        "pid": 165488,
        "tid": 139703678176448
    },
    {
        "name": "DoPutSync_",
        "ph": "E",
        "ts": 1705358086836794,
        "pid": 165488,
        "tid": 139703678176448
    },
    {
        "name": "DoPutSync_",
        "ph": "B",
        "ts": 1705358086836812,
        "pid": 165488,
        "tid": 139703678176448
    },
    {
        "name": "Put",
        "ph": "B",
        "ts": 1705358086836827,
        "pid": 165488,
        "tid": 139703678176448
    },
    {
        "name": "Put",
        "ph": "E",
        "ts": 1705358086836872,
        "pid": 165488,
        "tid": 139703678176448
    },
    {
        "name": "DoPutSync_",
        "ph": "E",
        "ts": 1705358086836977,
        "pid": 165488,
        "tid": 139703678176448
    },
    {
        "name": "DoPutSync_",
        "ph": "B",
        "ts": 1705358086836995,
        "pid": 165488,
        "tid": 139703678176448
    },
    {
        "name": "Put",
        "ph": "B",
        "ts": 1705358086837010,
        "pid": 165488,
        "tid": 139703678176448
    },
    {
        "name": "Put",
        "ph": "E",
        "ts": 1705358086837055,
        "pid": 165488,
        "tid": 139703678176448
    },
    {
        "name": "DoPutSync_",
        "ph": "E",
        "ts": 1705358086837161,
        "pid": 165488,
        "tid": 139703678176448
    },
    {
        "name": "DoPutSync_",
        "ph": "B",
        "ts": 1705358086837179,
        "pid": 165488,
        "tid": 139703678176448
    },
    {
        "name": "Put",
        "ph": "B",
        "ts": 1705358086837194,
        "pid": 165488,
        "tid": 139703678176448
    },
    {
        "name": "Put",
        "ph": "E",
        "ts": 1705358086837239,
        "pid": 165488,
        "tid": 139703678176448
    },
    {
        "name": "DoPutSync_",
        "ph": "E",
        "ts": 1705358086837337,
        "pid": 165488,
        "tid": 139703678176448
    },
    {
        "name": "DoPutSync_",
        "ph": "B",
        "ts": 1705358086837356,
        "pid": 165488,
        "tid": 139703678176448
    },
    {
        "name": "Put",
        "ph": "B",
        "ts": 1705358086837372,
        "pid": 165488,
        "tid": 139703678176448
    },
    {
        "name": "Put",
        "ph": "E",
        "ts": 1705358086837419,
        "pid": 165488,
        "tid": 139703678176448
    },
    {
        "name": "DoPutSync_",
        "ph": "E",
        "ts": 1705358086837520,
        "pid": 165488,
        "tid": 139703678176448
    },
    {
        "name": "DoPutSync_",
        "ph": "B",
        "ts": 1705358086837538,
        "pid": 165488,
        "tid": 139703678176448
    },
    {
        "name": "Put",
        "ph": "B",
        "ts": 1705358086837558,
        "pid": 165488,
        "tid": 139703678176448
    },
    {
        "name": "Put",
        "ph": "E",
        "ts": 1705358086837607,
        "pid": 165488,
        "tid": 139703678176448
    },
    {
        "name": "DoPutSync_",
        "ph": "E",
        "ts": 1705358086837717,
        "pid": 165488,
        "tid": 139703678176448
    },
    {
        "name": "DoPutSync_",
        "ph": "B",
        "ts": 1705358086837736,
        "pid": 165488,
        "tid": 139703678176448
    },
    {
        "name": "Put",
        "ph": "B",
        "ts": 1705358086837753,
        "pid": 165488,
        "tid": 139703678176448
    },
    {
        "name": "Put",
        "ph": "E",
        "ts": 1705358086837797,
        "pid": 165488,
        "tid": 139703678176448
    },
    {
        "name": "DoPutSync_",
        "ph": "E",
        "ts": 1705358086837912,
        "pid": 165488,
        "tid": 139703678176448
    },
    {
        "name": "DoPutSync_",
        "ph": "B",
        "ts": 1705358086837930,
        "pid": 165488,
        "tid": 139703678176448
    },
    {
        "name": "Put",
        "ph": "B",
        "ts": 1705358086837946,
        "pid": 165488,
        "tid": 139703678176448
    },
    {
        "name": "Put",
        "ph": "E",
        "ts": 1705358086837995,
        "pid": 165488,
        "tid": 139703678176448
    },
    {
        "name": "DoPutSync_",
        "ph": "E",
        "ts": 1705358086838101,
        "pid": 165488,
        "tid": 139703678176448
    },
    {
        "name": "DoPutDeferred_",
        "ph": "B",
        "ts": 1705358086838134,
        "pid": 165488,
        "tid": 139703678176448
    },
    {
        "name": "Put",
        "ph": "B",
        "ts": 1705358086838150,
        "pid": 165488,
        "tid": 139703678176448
    },
    {
        "name": "Put",
        "ph": "E",
        "ts": 1705358086838346,
        "pid": 165488,
        "tid": 139703678176448
    },
    {
        "name": "DoPutDeferred_",
        "ph": "E",
        "ts": 1705358086838464,
        "pid": 165488,
        "tid": 139703678176448
    },
    {
        "name": "EndStep",
        "ph": "B",
        "ts": 1705358086838483,
        "pid": 165488,
        "tid": 139703678176448
    },
    {
        "name": "EndStep",
        "ph": "E",
        "ts": 1705358086838583,
        "pid": 165488,
        "tid": 139703678176448
    },
    {
        "name": "BeginStep",
        "ph": "B",
        "ts": 1705358087202247,
        "pid": 165488,
        "tid": 139703678176448
    },
    {
        "name": "IncrementCurrentStep",
        "ph": "B",
        "ts": 1705358087202319,
        "pid": 165488,
        "tid": 139703678176448
    },
    {
        "name": "IncrementCurrentStep",
        "ph": "E",
        "ts": 1705358087202334,
        "pid": 165488,
        "tid": 139703678176448
    },
    {
        "name": "GetBucket",
        "ph": "B",
        "ts": 1705358087202383,
        "pid": 165488,
        "tid": 139703678176448
    },
    {
        "name": "BeginStep",
        "ph": "B",
        "ts": 1705358086835643,
        "pid": 165489,
        "tid": 140327299464384
    },
    {
        "name": "IncrementCurrentStep",
        "ph": "B",
        "ts": 1705358086835743,
        "pid": 165489,
        "tid": 140327299464384
    },
    {
        "name": "IncrementCurrentStep",
        "ph": "E",
        "ts": 1705358086835768,
        "pid": 165489,
        "tid": 140327299464384
    },
    {
        "name": "GetBucket",
        "ph": "B",
        "ts": 1705358086835815,
        "pid": 165489,
        "tid": 140327299464384
    },
    {
        "name": "GetBucket",
        "ph": "E",
        "ts": 1705358086837043,
        "pid": 165489,
        "tid": 140327299464384
    },
    {
        "name": "BeginStep",
        "ph": "E",
        "ts": 1705358086837104,
        "pid": 165489,
        "tid": 140327299464384
    },
    {
        "name": "DoPutSync_",
        "ph": "B",
        "ts": 1705358086837173,
        "pid": 165489,
        "tid": 140327299464384
    },
    {
        "name": "Put",
        "ph": "B",
        "ts": 1705358086837219,
        "pid": 165489,
        "tid": 140327299464384
    },
    {
        "name": "Put",
        "ph": "E",
        "ts": 1705358086837356,
        "pid": 165489,
        "tid": 140327299464384
    },
    {
        "name": "DoPutSync_",
        "ph": "E",
        "ts": 1705358086837881,
        "pid": 165489,
        "tid": 140327299464384
    },
    {
        "name": "DoPutSync_",
        "ph": "B",
        "ts": 1705358086837928,
        "pid": 165489,
        "tid": 140327299464384
    },
    {
        "name": "Put",
        "ph": "B",
        "ts": 1705358086837951,
        "pid": 165489,
        "tid": 140327299464384
    },
    {
        "name": "Put",
        "ph": "E",
        "ts": 1705358086838019,
        "pid": 165489,
        "tid": 140327299464384
    },
    {
        "name": "DoPutSync_",
        "ph": "E",
        "ts": 1705358086838172,
        "pid": 165489,
        "tid": 140327299464384
    },
    {
        "name": "DoPutSync_",
        "ph": "B",
        "ts": 1705358086838214,
        "pid": 165489,
        "tid": 140327299464384
    },
    {
        "name": "Put",
        "ph": "B",
        "ts": 1705358086838233,
        "pid": 165489,
        "tid": 140327299464384
    },
    {
        "name": "Put",
        "ph": "E",
        "ts": 1705358086838312,
        "pid": 165489,
        "tid": 140327299464384
    },
    {
        "name": "DoPutSync_",
        "ph": "E",
        "ts": 1705358086838462,
        "pid": 165489,
        "tid": 140327299464384
    },
    {
        "name": "DoPutSync_",
        "ph": "B",
        "ts": 1705358086838486,
        "pid": 165489,
        "tid": 140327299464384
    },
    {
        "name": "Put",
        "ph": "B",
        "ts": 1705358086838506,
        "pid": 165489,
        "tid": 140327299464384
    },
    {
        "name": "Put",
        "ph": "E",
        "ts": 1705358086838566,
        "pid": 165489,
        "tid": 140327299464384
    },
    {
        "name": "DoPutSync_",
        "ph": "E",
        "ts": 1705358086838702,
        "pid": 165489,
        "tid": 140327299464384
    },
    {
        "name": "DoPutSync_",
        "ph": "B",
        "ts": 1705358086838727,
        "pid": 165489,
        "tid": 140327299464384
    },
    {
        "name": "Put",
        "ph": "B",
        "ts": 1705358086838744,
        "pid": 165489,
        "tid": 140327299464384
    },
    {
        "name": "Put",
        "ph": "E",
        "ts": 1705358086838811,
        "pid": 165489,
        "tid": 140327299464384
    },
    {
        "name": "DoPutSync_",
        "ph": "E",
        "ts": 1705358086838939,
        "pid": 165489,
        "tid": 140327299464384
    },
    {
        "name": "DoPutSync_",
        "ph": "B",
        "ts": 1705358086838964,
        "pid": 165489,
        "tid": 140327299464384
    },
    {
        "name": "Put",
        "ph": "B",
        "ts": 1705358086838981,
        "pid": 165489,
        "tid": 140327299464384
    },
    {
        "name": "Put",
        "ph": "E",
        "ts": 1705358086839044,
        "pid": 165489,
        "tid": 140327299464384
    },
    {
        "name": "DoPutSync_",
        "ph": "E",
        "ts": 1705358086839164,
        "pid": 165489,
        "tid": 140327299464384
    },
    {
        "name": "DoPutSync_",
        "ph": "B",
        "ts": 1705358086839188,
        "pid": 165489,
        "tid": 140327299464384
    },
    {
        "name": "Put",
        "ph": "B",
        "ts": 1705358086839205,
        "pid": 165489,
        "tid": 140327299464384
    },
    {
        "name": "Put",
        "ph": "E",
        "ts": 1705358086839259,
        "pid": 165489,
        "tid": 140327299464384
    },
    {
        "name": "DoPutSync_",
        "ph": "E",
        "ts": 1705358086839397,
        "pid": 165489,
        "tid": 140327299464384
    },
    {
        "name": "DoPutSync_",
        "ph": "B",
        "ts": 1705358086839421,
        "pid": 165489,
        "tid": 140327299464384
    },
    {
        "name": "Put",
        "ph": "B",
        "ts": 1705358086839439,
        "pid": 165489,
        "tid": 140327299464384
    },
    {
        "name": "Put",
        "ph": "E",
        "ts": 1705358086839502,
        "pid": 165489,
        "tid": 140327299464384
    },
    {
        "name": "DoPutSync_",
        "ph": "E",
        "ts": 1705358086839626,
        "pid": 165489,
        "tid": 140327299464384
    },
    {
        "name": "DoPutSync_",
        "ph": "B",
        "ts": 1705358086839652,
        "pid": 165489,
        "tid": 140327299464384
    },
    {
        "name": "Put",
        "ph": "B",
        "ts": 1705358086839671,
        "pid": 165489,
        "tid": 140327299464384
    },
    {
        "name": "Put",
        "ph": "E",
        "ts": 1705358086839725,
        "pid": 165489,
        "tid": 140327299464384
    },
    {
        "name": "DoPutSync_",
        "ph": "E",
        "ts": 1705358086839847,
        "pid": 165489,
        "tid": 140327299464384
    },
    {
        "name": "DoPutSync_",
        "ph": "B",
        "ts": 1705358086839871,
        "pid": 165489,
        "tid": 140327299464384
    },
    {
        "name": "Put",
        "ph": "B",
        "ts": 1705358086839900,
        "pid": 165489,
        "tid": 140327299464384
    },
    {
        "name": "Put",
        "ph": "E",
        "ts": 1705358086839967,
        "pid": 165489,
        "tid": 140327299464384
    },
    {
        "name": "DoPutSync_",
        "ph": "E",
        "ts": 1705358086840092,
        "pid": 165489,
        "tid": 140327299464384
    },
    {
        "name": "DoPutSync_",
        "ph": "B",
        "ts": 1705358086840116,
        "pid": 165489,
        "tid": 140327299464384
    },
    {
        "name": "Put",
        "ph": "B",
        "ts": 1705358086840137,
        "pid": 165489,
        "tid": 140327299464384
    },
    {
        "name": "Put",
        "ph": "E",
        "ts": 1705358086840192,
        "pid": 165489,
        "tid": 140327299464384
    },
    {
        "name": "DoPutSync_",
        "ph": "E",
        "ts": 1705358086840343,
        "pid": 165489,
        "tid": 140327299464384
    },
    {
        "name": "DoPutSync_",
        "ph": "B",
        "ts": 1705358086840368,
        "pid": 165489,
        "tid": 140327299464384
    },
    {
        "name": "Put",
        "ph": "B",
        "ts": 1705358086840386,
        "pid": 165489,
        "tid": 140327299464384
    },
    {
        "name": "Put",
        "ph": "E",
        "ts": 1705358086840442,
        "pid": 165489,
        "tid": 140327299464384
    },
    {
        "name": "DoPutSync_",
        "ph": "E",
        "ts": 1705358086840583,
        "pid": 165489,
        "tid": 140327299464384
    },
    {
        "name": "DoPutDeferred_",
        "ph": "B",
        "ts": 1705358086840624,
        "pid": 165489,
        "tid": 140327299464384
    },
    {
        "name": "Put",
        "ph": "B",
        "ts": 1705358086840643,
        "pid": 165489,
        "tid": 140327299464384
    },
    {
        "name": "Put",
        "ph": "E",
        "ts": 1705358086840955,
        "pid": 165489,
        "tid": 140327299464384
    },
    {
        "name": "DoPutDeferred_",
        "ph": "E",
        "ts": 1705358086841093,
        "pid": 165489,
        "tid": 140327299464384
    },
    {
        "name": "EndStep",
        "ph": "B",
        "ts": 1705358086841118,
        "pid": 165489,
        "tid": 140327299464384
    },
    {
        "name": "EndStep",
        "ph": "E",
        "ts": 1705358086841188,
        "pid": 165489,
        "tid": 140327299464384
    },
    {
        "name": "BeginStep",
        "ph": "B",
        "ts": 1705358087213551,
        "pid": 165489,
        "tid": 140327299464384
    },
    {
        "name": "IncrementCurrentStep",
        "ph": "B",
        "ts": 1705358087213626,
        "pid": 165489,
        "tid": 140327299464384
    },
    {
        "name": "IncrementCurrentStep",
        "ph": "E",
        "ts": 1705358087213641,
        "pid": 165489,
        "tid": 140327299464384
    },
    {
        "name": "GetBucket",
        "ph": "B",
        "ts": 1705358087213690,
        "pid": 165489,
        "tid": 140327299464384
    },
    {
        "name": "BeginStep",
        "ph": "B",
        "ts": 1705358086834831,
        "pid": 165490,
        "tid": 139657661533376
    },
    {
        "name": "IncrementCurrentStep",
        "ph": "B",
        "ts": 1705358086834894,
        "pid": 165490,
        "tid": 139657661533376
    },
    {
        "name": "IncrementCurrentStep",
        "ph": "E",
        "ts": 1705358086834911,
        "pid": 165490,
        "tid": 139657661533376
    },
    {
        "name": "GetBucket",
        "ph": "B",
        "ts": 1705358086834955,
        "pid": 165490,
        "tid": 139657661533376
    },
    {
        "name": "GetBucket",
        "ph": "E",
        "ts": 1705358086835081,
        "pid": 165490,
        "tid": 139657661533376
    },
    {
        "name": "BeginStep",
        "ph": "E",
        "ts": 1705358086835123,
        "pid": 165490,
        "tid": 139657661533376
    },
    {
        "name": "DoPutSync_",
        "ph": "B",
        "ts": 1705358086835171,
        "pid": 165490,
        "tid": 139657661533376
    },
    {
        "name": "Put",
        "ph": "B",
        "ts": 1705358086835595,
        "pid": 165490,
        "tid": 139657661533376
    },
    {
        "name": "Put",
        "ph": "E",
        "ts": 1705358086835683,
        "pid": 165490,
        "tid": 139657661533376
    },
    {
        "name": "DoPutSync_",
        "ph": "E",
        "ts": 1705358086836011,
        "pid": 165490,
        "tid": 139657661533376
    },
    {
        "name": "DoPutSync_",
        "ph": "B",
        "ts": 1705358086836041,
        "pid": 165490,
        "tid": 139657661533376
    },
    {
        "name": "Put",
        "ph": "B",
        "ts": 1705358086836060,
        "pid": 165490,
        "tid": 139657661533376
    },
    {
        "name": "Put",
        "ph": "E",
        "ts": 1705358086836108,
        "pid": 165490,
        "tid": 139657661533376
    },
    {
        "name": "DoPutSync_",
        "ph": "E",
        "ts": 1705358086836215,
        "pid": 165490,
        "tid": 139657661533376
    },
    {
        "name": "DoPutSync_",
        "ph": "B",
        "ts": 1705358086836244,
        "pid": 165490,
        "tid": 139657661533376
    },
    {
        "name": "Put",
        "ph": "B",
        "ts": 1705358086836262,
        "pid": 165490,
        "tid": 139657661533376
    },
    {
        "name": "Put",
        "ph": "E",
        "ts": 1705358086836308,
        "pid": 165490,
        "tid": 139657661533376
    },
    {
        "name": "DoPutSync_",
        "ph": "E",
        "ts": 1705358086836423,
        "pid": 165490,
        "tid": 139657661533376
    },
    {
        "name": "DoPutSync_",
        "ph": "B",
        "ts": 1705358086836442,
        "pid": 165490,
        "tid": 139657661533376
    },
    {
        "name": "Put",
        "ph": "B",
        "ts": 1705358086836457,
        "pid": 165490,
        "tid": 139657661533376
    },
    {
        "name": "Put",
        "ph": "E",
        "ts": 1705358086836508,
        "pid": 165490,
        "tid": 139657661533376
    },
    {
        "name": "DoPutSync_",
        "ph": "E",
        "ts": 1705358086836608,
        "pid": 165490,
        "tid": 139657661533376
    },
    {
        "name": "DoPutSync_",
        "ph": "B",
        "ts": 1705358086836626,
        "pid": 165490,
        "tid": 139657661533376
    },
    {
        "name": "Put",
        "ph": "B",
        "ts": 1705358086836641,
        "pid": 165490,
        "tid": 139657661533376
    },
    {
        "name": "Put",
        "ph": "E",
        "ts": 1705358086836693,
        "pid": 165490,
        "tid": 139657661533376
    },
    {
        "name": "DoPutSync_",
        "ph": "E",
        "ts": 1705358086836792,
        "pid": 165490,
        "tid": 139657661533376
    },
    {
        "name": "DoPutSync_",
        "ph": "B",
        "ts": 1705358086836811,
        "pid": 165490,
        "tid": 139657661533376
    },
    {
        "name": "Put",
        "ph": "B",
        "ts": 1705358086836826,
        "pid": 165490,
        "tid": 139657661533376
    },
    {
        "name": "Put",
        "ph": "E",
        "ts": 1705358086836871,
        "pid": 165490,
        "tid": 139657661533376
    },
    {
        "name": "DoPutSync_",
        "ph": "E",
        "ts": 1705358086836968,
        "pid": 165490,
        "tid": 139657661533376
    },
    {
        "name": "DoPutSync_",
        "ph": "B",
        "ts": 1705358086836990,
        "pid": 165490,
        "tid": 139657661533376
    },
    {
        "name": "Put",
        "ph": "B",
        "ts": 1705358086837006,
        "pid": 165490,
        "tid": 139657661533376
    },
    {
        "name": "Put",
        "ph": "E",
        "ts": 1705358086837052,
        "pid": 165490,
        "tid": 139657661533376
    },
    {
        "name": "DoPutSync_",
        "ph": "E",
        "ts": 1705358086837162,
        "pid": 165490,
        "tid": 139657661533376
    },
    {
        "name": "DoPutSync_",
        "ph": "B",
        "ts": 1705358086837180,
        "pid": 165490,
        "tid": 139657661533376
    },
    {
        "name": "Put",
        "ph": "B",
        "ts": 1705358086837195,
        "pid": 165490,
        "tid": 139657661533376
    },
    {
        "name": "Put",
        "ph": "E",
        "ts": 1705358086837240,
        "pid": 165490,
        "tid": 139657661533376
    },
    {
        "name": "DoPutSync_",
        "ph": "E",
        "ts": 1705358086837339,
        "pid": 165490,
        "tid": 139657661533376
    },
    {
        "name": "DoPutSync_",
        "ph": "B",
        "ts": 1705358086837359,
        "pid": 165490,
        "tid": 139657661533376
    },
    {
        "name": "Put",
        "ph": "B",
        "ts": 1705358086837374,
        "pid": 165490,
        "tid": 139657661533376
    },
    {
        "name": "Put",
        "ph": "E",
        "ts": 1705358086837422,
        "pid": 165490,
        "tid": 139657661533376
    },
    {
        "name": "DoPutSync_",
        "ph": "E",
        "ts": 1705358086837521,
        "pid": 165490,
        "tid": 139657661533376
    },
    {
        "name": "DoPutSync_",
        "ph": "B",
        "ts": 1705358086837540,
        "pid": 165490,
        "tid": 139657661533376
    },
    {
        "name": "Put",
        "ph": "B",
        "ts": 1705358086837560,
        "pid": 165490,
        "tid": 139657661533376
    },
    {
        "name": "Put",
        "ph": "E",
        "ts": 1705358086837619,
        "pid": 165490,
        "tid": 139657661533376
    },
    {
        "name": "DoPutSync_",
        "ph": "E",
        "ts": 1705358086837724,
        "pid": 165490,
        "tid": 139657661533376
    },
    {
        "name": "DoPutSync_",
        "ph": "B",
        "ts": 1705358086837744,
        "pid": 165490,
        "tid": 139657661533376
    },
    {
        "name": "Put",
        "ph": "B",
        "ts": 1705358086837760,
        "pid": 165490,
        "tid": 139657661533376
    },
    {
        "name": "Put",
        "ph": "E",
        "ts": 1705358086837809,
        "pid": 165490,
        "tid": 139657661533376
    },
    {
        "name": "DoPutSync_",
        "ph": "E",
        "ts": 1705358086837926,
        "pid": 165490,
        "tid": 139657661533376
    },
    {
        "name": "DoPutSync_",
        "ph": "B",
        "ts": 1705358086837945,
        "pid": 165490,
        "tid": 139657661533376
    },
    {
        "name": "Put",
        "ph": "B",
        "ts": 1705358086837961,
        "pid": 165490,
        "tid": 139657661533376
    },
    {
        "name": "Put",
        "ph": "E",
        "ts": 1705358086838009,
        "pid": 165490,
        "tid": 139657661533376
    },
    {
        "name": "DoPutSync_",
        "ph": "E",
        "ts": 1705358086838113,
        "pid": 165490,
        "tid": 139657661533376
    },
    {
        "name": "DoPutDeferred_",
        "ph": "B",
        "ts": 1705358086838142,
        "pid": 165490,
        "tid": 139657661533376
    },
    {
        "name": "Put",
        "ph": "B",
        "ts": 1705358086838158,
        "pid": 165490,
        "tid": 139657661533376
    },
    {
        "name": "Put",
        "ph": "E",
        "ts": 1705358086838355,
        "pid": 165490,
        "tid": 139657661533376
    },
    {
        "name": "DoPutDeferred_",
        "ph": "E",
        "ts": 1705358086838470,
        "pid": 165490,
        "tid": 139657661533376
    },
    {
        "name": "EndStep",
        "ph": "B",
        "ts": 1705358086838488,
        "pid": 165490,
        "tid": 139657661533376
    },
    {
        "name": "EndStep",
        "ph": "E",
        "ts": 1705358086838557,
        "pid": 165490,
        "tid": 139657661533376
    },
    {
        "name": "BeginStep",
        "ph": "B",
        "ts": 1705358087203965,
        "pid": 165490,
        "tid": 139657661533376
    },
    {
        "name": "IncrementCurrentStep",
        "ph": "B",
        "ts": 1705358087204040,
        "pid": 165490,
        "tid": 139657661533376
    },
    {
        "name": "IncrementCurrentStep",
        "ph": "E",
        "ts": 1705358087204057,
        "pid": 165490,
        "tid": 139657661533376
    },
    {
        "name": "GetBucket",
        "ph": "B",
        "ts": 1705358087204106,
        "pid": 165490,
        "tid": 139657661533376
    },
    {
        "name": "BeginStep",
        "ph": "B",
        "ts": 1705358086835318,
        "pid": 165491,
        "tid": 139912003030208
    },
    {
        "name": "IncrementCurrentStep",
        "ph": "B",
        "ts": 1705358086835380,
        "pid": 165491,
        "tid": 139912003030208
    },
    {
        "name": "IncrementCurrentStep",
        "ph": "E",
        "ts": 1705358086835398,
        "pid": 165491,
        "tid": 139912003030208
    },
    {
        "name": "GetBucket",
        "ph": "B",
        "ts": 1705358086835438,
        "pid": 165491,
        "tid": 139912003030208
    },
    {
        "name": "GetBucket",
        "ph": "E",
        "ts": 1705358086836029,
        "pid": 165491,
        "tid": 139912003030208
    },
    {
        "name": "BeginStep",
        "ph": "E",
        "ts": 1705358086836073,
        "pid": 165491,
        "tid": 139912003030208
    },
    {
        "name": "DoPutSync_",
        "ph": "B",
        "ts": 1705358086836114,
        "pid": 165491,
        "tid": 139912003030208
    },
    {
        "name": "Put",
        "ph": "B",
        "ts": 1705358086836139,
        "pid": 165491,
        "tid": 139912003030208
    },
    {
        "name": "Put",
        "ph": "E",
        "ts": 1705358086836220,
        "pid": 165491,
        "tid": 139912003030208
    },
    {
        "name": "DoPutSync_",
        "ph": "E",
        "ts": 1705358086836543,
        "pid": 165491,
        "tid": 139912003030208
    },
    {
        "name": "DoPutSync_",
        "ph": "B",
        "ts": 1705358086836574,
        "pid": 165491,
        "tid": 139912003030208
    },
    {
        "name": "Put",
        "ph": "B",
        "ts": 1705358086836597,
        "pid": 165491,
        "tid": 139912003030208
    },
    {
        "name": "Put",
        "ph": "E",
        "ts": 1705358086836647,
        "pid": 165491,
        "tid": 139912003030208
    },
    {
        "name": "DoPutSync_",
        "ph": "E",
        "ts": 1705358086836760,
        "pid": 165491,
        "tid": 139912003030208
    },
    {
        "name": "DoPutSync_",
        "ph": "B",
        "ts": 1705358086836787,
        "pid": 165491,
        "tid": 139912003030208
    },
    {
        "name": "Put",
        "ph": "B",
        "ts": 1705358086836805,
        "pid": 165491,
        "tid": 139912003030208
    },
    {
        "name": "Put",
        "ph": "E",
        "ts": 1705358086836856,
        "pid": 165491,
        "tid": 139912003030208
    },
    {
        "name": "DoPutSync_",
        "ph": "E",
        "ts": 1705358086836968,
        "pid": 165491,
        "tid": 139912003030208
    },
    {
        "name": "DoPutSync_",
        "ph": "B",
        "ts": 1705358086836986,
        "pid": 165491,
        "tid": 139912003030208
    },
    {
        "name": "Put",
        "ph": "B",
        "ts": 1705358086837001,
        "pid": 165491,
        "tid": 139912003030208
    },
    {
        "name": "Put",
        "ph": "E",
        "ts": 1705358086837051,
        "pid": 165491,
        "tid": 139912003030208
    },
    {
        "name": "DoPutSync_",
        "ph": "E",
        "ts": 1705358086837151,
        "pid": 165491,
        "tid": 139912003030208
    },
    {
        "name": "DoPutSync_",
        "ph": "B",
        "ts": 1705358086837169,
        "pid": 165491,
        "tid": 139912003030208
    },
    {
        "name": "Put",
        "ph": "B",
        "ts": 1705358086837184,
        "pid": 165491,
        "tid": 139912003030208
    },
    {
        "name": "Put",
        "ph": "E",
        "ts": 1705358086837237,
        "pid": 165491,
        "tid": 139912003030208
    },
    {
        "name": "DoPutSync_",
        "ph": "E",
        "ts": 1705358086837349,
        "pid": 165491,
        "tid": 139912003030208
    },
    {
        "name": "DoPutSync_",
        "ph": "B",
        "ts": 1705358086837368,
        "pid": 165491,
        "tid": 139912003030208
    },
    {
        "name": "Put",
        "ph": "B",
        "ts": 1705358086837383,
        "pid": 165491,
        "tid": 139912003030208
    },
    {
        "name": "Put",
        "ph": "E",
        "ts": 1705358086837428,
        "pid": 165491,
        "tid": 139912003030208
    },
    {
        "name": "DoPutSync_",
        "ph": "E",
        "ts": 1705358086837528,
        "pid": 165491,
        "tid": 139912003030208
    },
    {
        "name": "DoPutSync_",
        "ph": "B",
        "ts": 1705358086837546,
        "pid": 165491,
        "tid": 139912003030208
    },
    {
        "name": "Put",
        "ph": "B",
        "ts": 1705358086837561,
        "pid": 165491,
        "tid": 139912003030208
    },
    {
        "name": "Put",
        "ph": "E",
        "ts": 1705358086837613,
        "pid": 165491,
        "tid": 139912003030208
    },
    {
        "name": "DoPutSync_",
        "ph": "E",
        "ts": 1705358086837727,
        "pid": 165491,
        "tid": 139912003030208
    },
    {
        "name": "DoPutSync_",
        "ph": "B",
        "ts": 1705358086837745,
        "pid": 165491,
        "tid": 139912003030208
    },
    {
        "name": "Put",
        "ph": "B",
        "ts": 1705358086837761,
        "pid": 165491,
        "tid": 139912003030208
    },
    {
        "name": "Put",
        "ph": "E",
        "ts": 1705358086837816,
        "pid": 165491,
        "tid": 139912003030208
    },
    {
        "name": "DoPutSync_",
        "ph": "E",
        "ts": 1705358086837921,
        "pid": 165491,
        "tid": 139912003030208
    },
    {
        "name": "DoPutSync_",
        "ph": "B",
        "ts": 1705358086837940,
        "pid": 165491,
        "tid": 139912003030208
    },
    {
        "name": "Put",
        "ph": "B",
        "ts": 1705358086837955,
        "pid": 165491,
        "tid": 139912003030208
    },
    {
        "name": "Put",
        "ph": "E",
        "ts": 1705358086838003,
        "pid": 165491,
        "tid": 139912003030208
    },
    {
        "name": "DoPutSync_",
        "ph": "E",
        "ts": 1705358086838104,
        "pid": 165491,
        "tid": 139912003030208
    },
    {
        "name": "DoPutSync_",
        "ph": "B",
        "ts": 1705358086838122,
        "pid": 165491,
        "tid": 139912003030208
    },
    {
        "name": "Put",
        "ph": "B",
        "ts": 1705358086838144,
        "pid": 165491,
        "tid": 139912003030208
    },
    {
        "name": "Put",
        "ph": "E",
        "ts": 1705358086838195,
        "pid": 165491,
        "tid": 139912003030208
    },
    {
        "name": "DoPutSync_",
        "ph": "E",
        "ts": 1705358086838300,
        "pid": 165491,
        "tid": 139912003030208
    },
    {
        "name": "DoPutSync_",
        "ph": "B",
        "ts": 1705358086838320,
        "pid": 165491,
        "tid": 139912003030208
    },
    {
        "name": "Put",
        "ph": "B",
        "ts": 1705358086838337,
        "pid": 165491,
        "tid": 139912003030208
    },
    {
        "name": "Put",
        "ph": "E",
        "ts": 1705358086838399,
        "pid": 165491,
        "tid": 139912003030208
    },
    {
        "name": "DoPutSync_",
        "ph": "E",
        "ts": 1705358086838516,
        "pid": 165491,
        "tid": 139912003030208
    },
    {
        "name": "DoPutSync_",
        "ph": "B",
        "ts": 1705358086838537,
        "pid": 165491,
        "tid": 139912003030208
    },
    {
        "name": "Put",
        "ph": "B",
        "ts": 1705358086838553,
        "pid": 165491,
        "tid": 139912003030208
    },
    {
        "name": "Put",
        "ph": "E",
        "ts": 1705358086838606,
        "pid": 165491,
        "tid": 139912003030208
    },
    {
        "name": "DoPutSync_",
        "ph": "E",
        "ts": 1705358086838713,
        "pid": 165491,
        "tid": 139912003030208
    },
    {
        "name": "DoPutDeferred_",
        "ph": "B",
        "ts": 1705358086838741,
        "pid": 165491,
        "tid": 139912003030208
    },
    {
        "name": "Put",
        "ph": "B",
        "ts": 1705358086838757,
        "pid": 165491,
        "tid": 139912003030208
    },
    {
        "name": "Put",
        "ph": "E",
        "ts": 1705358086838940,
        "pid": 165491,
        "tid": 139912003030208
    },
    {
        "name": "DoPutDeferred_",
        "ph": "E",
        "ts": 1705358086839054,
        "pid": 165491,
        "tid": 139912003030208
    },
    {
        "name": "EndStep",
        "ph": "B",
        "ts": 1705358086839072,
        "pid": 165491,
        "tid": 139912003030208
    },
    {
        "name": "EndStep",
        "ph": "E",
        "ts": 1705358086839137,
        "pid": 165491,
        "tid": 139912003030208
    },
    {
        "name": "BeginStep",
        "ph": "B",
        "ts": 1705358087203277,
        "pid": 165491,
        "tid": 139912003030208
    },
    {
        "name": "IncrementCurrentStep",
        "ph": "B",
        "ts": 1705358087203351,
        "pid": 165491,
        "tid": 139912003030208
    },
    {
        "name": "IncrementCurrentStep",
        "ph": "E",
        "ts": 1705358087203367,
        "pid": 165491,
        "tid": 139912003030208
    },
    {
        "name": "GetBucket",
        "ph": "B",
        "ts": 1705358087203415,
        "pid": 165491,
        "tid": 139912003030208
    }
]